{
  "content_disposition": "",
  "downloaded_at": "2026-02-07T11:32:20+00:00",
  "etag": "\"5fecef235fcc05bf5e9e9ee520b719e6\"",
  "file_path": "data/raw/069f5745eea7-utilities-efta00008428pdf/EFTA00008428.pdf",
  "id": "069f5745eea7-utilities-efta00008428pdf",
  "is_official": true,
  "last_modified": "Fri, 19 Dec 2025 23:31:09 GMT",
  "license_or_terms": "as published by source",
  "mime_type": "application/pdf",
  "notes": "DOJ Epstein Library disclosures released under the Epstein Files Transparency Act, including data set files and supplemental releases.",
  "pages": 1,
  "release_date": "2026-01-30",
  "sha256": "069f5745eea73606c55dbaa3b4cf00c8d3172c8eb4988a813d54ab9daaf6bc2d",
  "source_name": "DOJ Epstein Library \u2014 DOJ Disclosures",
  "source_page": "https://www.justice.gov/epstein/doj-disclosures/data-set-5-files",
  "source_url": "https://www.justice.gov/epstein/files/DataSet%205/EFTA00008428.pdf",
  "sources": [
    {
      "source_name": "DOJ Epstein Library \u2014 DOJ Disclosures",
      "source_url": "https://www.justice.gov/epstein/doj-disclosures/data-set-5-files"
    }
  ],
  "tags": [
    "doj",
    "epstein-library",
    "doj-disclosures"
  ],
  "title": "Utilities \u2014 EFTA00008428.pdf"
}
